pybotvac/__init__.py
pybotvac/account.py
pybotvac/exceptions.py
pybotvac/neato.py
pybotvac/robot.py
pybotvac/session.py
pybotvac/version.py
pybotvac/vorwerk.py
pybotvac/cert/ksecosys.com.crt
pybotvac-0.0.28.dist-info/LICENSE
pybotvac-0.0.28.dist-info/METADATA
pybotvac-0.0.28.dist-info/WHEEL
pybotvac-0.0.28.dist-info/top_level.txt
pybotvac-0.0.28.dist-info/RECORD
