Metadata-Version: 2.1
Name: pybotvac
Version: 0.0.28
Summary: Python package for controlling Neato pybotvac Connected vacuum robot
Home-page: https://github.com/stianaske/pybotvac
Author: Stian Askeland
Author-email: stianaske@gmail.com
License: Licensed under the MIT license. See LICENSE file for details
License-File: LICENSE
Requires-Dist: requests
Requires-Dist: requests-oauthlib
Requires-Dist: voluptuous
